test_pypi/__init__.py
test_pypi/print_srt.py
test_pypi_xuelang-0.0.1.dist-info/METADATA
test_pypi_xuelang-0.0.1.dist-info/WHEEL
test_pypi_xuelang-0.0.1.dist-info/top_level.txt
test_pypi_xuelang-0.0.1.dist-info/RECORD
