Metadata-Version: 2.1
Name: test-pypi-xuelang
Version: 0.0.1
Summary: PyPI test
Home-page: UNKNOWN
Author: wunsch
Author-email: wunsch0106@gmail.com
License: UNKNOWN
Platform: UNKNOWN
Classifier: Programming Language :: Python :: 3
Classifier: License :: OSI Approved :: MIT License
Classifier: Operating System :: OS Independent
